SparseAEH/__init__.py
SparseAEH/base.py
SparseAEH/function.py
SparseAEH/plot.py
SparseAEH-0.1.0.dist-info/METADATA
SparseAEH-0.1.0.dist-info/WHEEL
SparseAEH-0.1.0.dist-info/top_level.txt
SparseAEH-0.1.0.dist-info/RECORD
